[
  {
    "type": "menu",
    "key": "home",
    "page_name": "Home",
    "page-zuid": "7-b89e898090-3qsz5k",
    "parent": null
  },
  {
    "type": "menu",
    "key": "services",
    "page_name": "Services",
    "page-zuid": null,
    "parent": null
  },
  {
    "type": "menu",
    "key": null,
    "page_name": "Holiday Giving",
    "page-zuid": "7-f6b2f5c0be-lzt4xr",
    "sort": 0,
    "parent": "services"
  },
  {
    "type": "menu",
    "key": null,
    "page_name": "Spiritual and Worship Services",
    "page-zuid": "7-dac6fe9ce6-5wz9d1",
    "sort": 1,
    "parent": "services"
  },
  {
    "type": "menu",
    "key": null,
    "page_name": "Youth Services",
    "page-zuid": "7-fca3a79bf3-xdlxg0",
    "sort": 2,
    "parent": "services"
  },
  {
    "type": "menu",
    "key": null,
    "page_name": "Food Pantries",
    "page-zuid": "7-90a3b5d5df-snpl39",
    "sort": 3,
    "parent": "services"
  },
  {
    "type": "menu",
    "key": null,
    "page_name": "Family Counseling",
    "page-zuid": "7-a8a592e2ec-08wjbl",
    "sort": 4,
    "parent": "services"
  },
  {
    "type": "menu",
    "key": "about_us",
    "page_name": "About Us",
    "page-zuid": null,
    "parent": null
  },
  {
    "type": "menu",
    "key": null,
    "page_name": "About Us",
    "page-zuid": "7-c4afe1c9be-7wmzb5",
    "sort": 0,
    "parent": "about_us"
  },
  {
    "type": "menu",
    "key": null,
    "page_name": "Commitment to all",
    "page-zuid": "7-90eff9e999-tpj14d",
    "sort": 1,
    "parent": "about_us"
  },
  {
    "type": "menu",
    "key": null,
    "page_name": "Leadership Test (copy) (copy)",
    "page-zuid": "7-cce3cd8285-t1l58m",
    "sort": 2,
    "parent": "about_us"
  },
  {
    "type": "menu",
    "key": null,
    "page_name": "History",
    "page-zuid": "7-b8c09b84c2-fp57hm",
    "sort": 3,
    "parent": "about_us"
  },
  {
    "type": "menu",
    "key": null,
    "page_name": "Employment Opportunities",
    "page-zuid": "7-f8a8bcdbd3-2vljtw",
    "sort": 4,
    "parent": "about_us"
  },
  {
    "type": "menu",
    "key": null,
    "page_name": "Give With Joy",
    "page-zuid": "give_with_joy",
    "sort": 5,
    "parent": "about_us"
  },
  {
    "type": "menu",
    "key": "events",
    "page_name": "PASADENA (Tabernacle), CA: Corps Community Center",
    "page-zuid": "7-acc9b7cae8-54glph",
    "parent": null
  },
  {
    "type": "menu",
    "key": "newsroom",
    "page_name": "PASADENA (Tabernacle), CA: Corps Community Center",
    "page-zuid": "7-d2f5e58ec9-1kccc4",
    "parent": null
  },
  {
    "type": "menu",
    "key": "ways_to_give",
    "page_name": "Ways to give",
    "page-zuid": null,
    "parent": null
  },
  {
    "type": "menu",
    "key": null,
    "page_name": "Donate Money",
    "page-zuid": "donate_money",
    "sort": 0,
    "parent": "ways_to_give"
  },
  {
    "type": "menu",
    "key": null,
    "page_name": "Donate Goods",
    "page-zuid": "donate_goods",
    "sort": 1,
    "parent": "ways_to_give"
  },
  {
    "type": "menu",
    "key": null,
    "page_name": "Become a Fundraiser",
    "page-zuid": "become_fundraiser",
    "sort": 2,
    "parent": "ways_to_give"
  },
  {
    "type": "menu",
    "key": null,
    "page_name": "Planned Giving",
    "page-zuid": "7-f2b287aed9-0p8rkp",
    "sort": 3,
    "parent": "ways_to_give"
  },
  {
    "type": "menu",
    "key": null,
    "page_name": "Gift Stocks & Bonds",
    "page-zuid": "7-ceb9aec38c-jg599w",
    "sort": 4,
    "parent": "ways_to_give"
  },
  {
    "type": "menu",
    "key": null,
    "page_name": "Volunteer",
    "page-zuid": "7-cebb9ebd81-vzp4w7",
    "sort": 5,
    "parent": "ways_to_give"
  },
  {
    "type": "menu",
    "key": null,
    "page_name": "View All Ways to Give",
    "page-zuid": "7-9ef983beef-swgfd3",
    "sort": 6,
    "parent": "ways_to_give"
  },
  {
    "type": "menu",
    "key": "contact_us",
    "page_name": "Contact Us",
    "page-zuid": "7-bce9ca8ddd-pfclhx",
    "parent": null
  }
]