[
  {
    "type": "menu",
    "key": "home",
    "page_name": "Home",
    "page-zuid": "7-bcdbade785-7t7bgf",
    "parent": null
  },
  {
    "type": "menu",
    "key": "services",
    "page_name": "Services",
    "page-zuid": null,
    "parent": null
  },
  {
    "type": "menu",
    "key": null,
    "page_name": "Spiritual Healing",
    "page-zuid": "7-e2dff69d93-bh736r",
    "sort": 0,
    "parent": "services"
  },
  {
    "type": "menu",
    "key": null,
    "page_name": "Adult Program Services",
    "page-zuid": "7-cec8ead699-fl8s65",
    "sort": 1,
    "parent": "services"
  },
  {
    "type": "menu",
    "key": null,
    "page_name": "Food Pantries",
    "page-zuid": "7-8ef98cda8c-qxbnt6",
    "sort": 2,
    "parent": "services"
  },
  {
    "type": "menu",
    "key": null,
    "page_name": "Family Counseling",
    "page-zuid": "7-989bf695a0-2pwbww",
    "sort": 3,
    "parent": "services"
  },
  {
    "type": "menu",
    "key": null,
    "page_name": "Homelessness",
    "page-zuid": "7-aaa5e29f86-zn5mts",
    "sort": 4,
    "parent": "services"
  },
  {
    "type": "menu",
    "key": null,
    "page_name": "Disaster Relief",
    "page-zuid": "7-94c483d3ff-2qwpmq",
    "sort": 5,
    "parent": "services"
  },
  {
    "type": "menu",
    "key": "about_us",
    "page_name": "About Us",
    "page-zuid": null,
    "parent": null
  },
  {
    "type": "menu",
    "key": null,
    "page_name": "About Us",
    "page-zuid": "7-f2bffac2d5-bbssc9",
    "sort": 0,
    "parent": "about_us"
  },
  {
    "type": "menu",
    "key": null,
    "page_name": "Commitment to all",
    "page-zuid": "7-90eff9e999-tpj14d",
    "sort": 1,
    "parent": "about_us"
  },
  {
    "type": "menu",
    "key": null,
    "page_name": "Leadership",
    "page-zuid": "7-92d0c8d6de-3vqc4g",
    "sort": 2,
    "parent": "about_us"
  },
  {
    "type": "menu",
    "key": null,
    "page_name": "History",
    "page-zuid": "7-b8c09b84c2-fp57hm",
    "sort": 3,
    "parent": "about_us"
  },
  {
    "type": "menu",
    "key": null,
    "page_name": "Employment Opportunities",
    "page-zuid": "7-88deb6e6f5-l6xv5v",
    "sort": 4,
    "parent": "about_us"
  },
  {
    "type": "menu",
    "key": null,
    "page_name": "Give With Joy",
    "page-zuid": "give_with_joy",
    "sort": 5,
    "parent": "about_us"
  },
  {
    "type": "menu",
    "key": "events",
    "page_name": "Victoria Corps",
    "page-zuid": "7-d0baf9ff86-f06xz8",
    "parent": null
  },
  {
    "type": "menu",
    "key": "newsroom",
    "page_name": "Victoria Corps",
    "page-zuid": "7-b0c4a7beeb-khw689",
    "parent": null
  },
  {
    "type": "menu",
    "key": "ways_to_give",
    "page_name": "Ways to give",
    "page-zuid": null,
    "parent": null
  },
  {
    "type": "menu",
    "key": null,
    "page_name": "Donate Money",
    "page-zuid": "donate_money",
    "sort": 0,
    "parent": "ways_to_give"
  },
  {
    "type": "menu",
    "key": null,
    "page_name": "Donate Goods",
    "page-zuid": "donate_goods",
    "sort": 1,
    "parent": "ways_to_give"
  },
  {
    "type": "menu",
    "key": null,
    "page_name": "Become a Fundraiser",
    "page-zuid": "become_fundraiser",
    "sort": 2,
    "parent": "ways_to_give"
  },
  {
    "type": "menu",
    "key": null,
    "page_name": "Planned Giving",
    "page-zuid": "7-deb1f3c292-8n177t",
    "sort": 3,
    "parent": "ways_to_give"
  },
  {
    "type": "menu",
    "key": null,
    "page_name": "Gift Stocks & Bonds",
    "page-zuid": "7-e8b8d68ccc-t4mw4d",
    "sort": 4,
    "parent": "ways_to_give"
  },
  {
    "type": "menu",
    "key": null,
    "page_name": "Volunteer",
    "page-zuid": "7-e486fce0d9-h2mflh",
    "sort": 5,
    "parent": "ways_to_give"
  },
  {
    "type": "menu",
    "key": null,
    "page_name": "View All Ways to Give",
    "page-zuid": "7-eceab6f8eb-03112w",
    "sort": 6,
    "parent": "ways_to_give"
  },
  {
    "type": "menu",
    "key": "contact_us",
    "page_name": "Contact Us",
    "page-zuid": "7-d88ad0d5f0-7w7m6l",
    "parent": null
  }
]