[
  {
    "type": "menu",
    "key": "home",
    "page_name": "Home",
    "page-zuid": "7-cee2988299-196vpv",
    "parent": null
  },
  {
    "type": "menu",
    "key": "services",
    "page_name": "Services",
    "page-zuid": null,
    "parent": null
  },
  {
    "type": "menu",
    "key": null,
    "page_name": "Spiritual Healing",
    "page-zuid": "7-f8ebdac2d9-5j3p0x",
    "sort": 0,
    "parent": "services"
  },
  {
    "type": "menu",
    "key": null,
    "page_name": "Senior Services",
    "page-zuid": "7-b6f1a68ad3-7m335h",
    "sort": 1,
    "parent": "services"
  },
  {
    "type": "menu",
    "key": null,
    "page_name": "Family Counseling",
    "page-zuid": "7-98d784cfe6-pm5lt5",
    "sort": 2,
    "parent": "services"
  },
  {
    "type": "menu",
    "key": null,
    "page_name": "Food Pantries",
    "page-zuid": "7-bea1ffc8cc-k0c85x",
    "sort": 3,
    "parent": "services"
  },
  {
    "type": "menu",
    "key": null,
    "page_name": "Adult Program Services",
    "page-zuid": "7-8e86b58ae0-149zk6",
    "sort": 4,
    "parent": "services"
  },
  {
    "type": "menu",
    "key": null,
    "page_name": "Youth Services",
    "page-zuid": "7-faf9c390ed-2f88xm",
    "sort": 5,
    "parent": "services"
  },
  {
    "type": "menu",
    "key": null,
    "page_name": "Disaster Relief",
    "page-zuid": "7-d4d0e78ec6-j2fctr",
    "sort": 6,
    "parent": "services"
  },
  {
    "type": "menu",
    "key": "about_us",
    "page_name": "About Us",
    "page-zuid": null,
    "parent": null
  },
  {
    "type": "menu",
    "key": null,
    "page_name": "About Us",
    "page-zuid": "7-f8c1b99f8b-x1n83b",
    "sort": 0,
    "parent": "about_us"
  },
  {
    "type": "menu",
    "key": null,
    "page_name": "Commitment to all",
    "page-zuid": "7-90eff9e999-tpj14d",
    "sort": 1,
    "parent": "about_us"
  },
  {
    "type": "menu",
    "key": null,
    "page_name": "Leadership",
    "page-zuid": "7-9ea0dc89d8-m560pm",
    "sort": 2,
    "parent": "about_us"
  },
  {
    "type": "menu",
    "key": null,
    "page_name": "History",
    "page-zuid": "7-b8c09b84c2-fp57hm",
    "sort": 3,
    "parent": "about_us"
  },
  {
    "type": "menu",
    "key": null,
    "page_name": "Employment Opportunities",
    "page-zuid": "7-88deb6e6f5-l6xv5v",
    "sort": 4,
    "parent": "about_us"
  },
  {
    "type": "menu",
    "key": null,
    "page_name": "Give With Joy",
    "page-zuid": "give_with_joy",
    "sort": 5,
    "parent": "about_us"
  },
  {
    "type": "menu",
    "key": "events",
    "page_name": "Houston Temple Corps",
    "page-zuid": "7-e4f0d5b3ca-7810nl",
    "parent": null
  },
  {
    "type": "menu",
    "key": "newsroom",
    "page_name": "Houston Temple Corps",
    "page-zuid": "7-98cfd3e0ae-nxr21g",
    "parent": null
  },
  {
    "type": "menu",
    "key": "ways_to_give",
    "page_name": "Ways to give",
    "page-zuid": null,
    "parent": null
  },
  {
    "type": "menu",
    "key": null,
    "page_name": "Donate Money",
    "page-zuid": "donate_money",
    "sort": 0,
    "parent": "ways_to_give"
  },
  {
    "type": "menu",
    "key": null,
    "page_name": "Donate Goods",
    "page-zuid": "donate_goods",
    "sort": 1,
    "parent": "ways_to_give"
  },
  {
    "type": "menu",
    "key": null,
    "page_name": "Become a Fundraiser",
    "page-zuid": "become_fundraiser",
    "sort": 2,
    "parent": "ways_to_give"
  },
  {
    "type": "menu",
    "key": null,
    "page_name": "Planned Giving",
    "page-zuid": "7-deb1f3c292-8n177t",
    "sort": 3,
    "parent": "ways_to_give"
  },
  {
    "type": "menu",
    "key": null,
    "page_name": "Gift Stocks & Bonds",
    "page-zuid": "7-e8b8d68ccc-t4mw4d",
    "sort": 4,
    "parent": "ways_to_give"
  },
  {
    "type": "menu",
    "key": null,
    "page_name": "Volunteer",
    "page-zuid": "7-e486fce0d9-h2mflh",
    "sort": 5,
    "parent": "ways_to_give"
  },
  {
    "type": "menu",
    "key": null,
    "page_name": "View All Ways to Give",
    "page-zuid": "7-eceab6f8eb-03112w",
    "sort": 6,
    "parent": "ways_to_give"
  },
  {
    "type": "menu",
    "key": "contact_us",
    "page_name": "Contact Us",
    "page-zuid": "7-988d81a2a8-f91h55",
    "parent": null
  }
]