[
  {
    "type": "menu",
    "key": "home",
    "page_name": "Home",
    "page-zuid": "7-e0ddaea9d3-1d4nks",
    "parent": null
  },
  {
    "type": "menu",
    "key": "services",
    "page_name": "Services",
    "page-zuid": null,
    "parent": null
  },
  {
    "type": "menu",
    "key": null,
    "page_name": "Food Programs",
    "page-zuid": "7-a8d6edb0a5-53052r",
    "sort": 0,
    "parent": "services"
  },
  {
    "type": "menu",
    "key": null,
    "page_name": "Assistance Programs",
    "page-zuid": "7-90b6c090b9-ksh4qd",
    "sort": 1,
    "parent": "services"
  },
  {
    "type": "menu",
    "key": null,
    "page_name": "Senior Services",
    "page-zuid": "7-b6d78a8aac-bv94l6",
    "sort": 2,
    "parent": "services"
  },
  {
    "type": "menu",
    "key": null,
    "page_name": "Music Programs",
    "page-zuid": "7-e4dececba7-308k09",
    "sort": 3,
    "parent": "services"
  },
  {
    "type": "menu",
    "key": null,
    "page_name": "Youth Services",
    "page-zuid": "7-849da3d9bf-g53n61",
    "sort": 4,
    "parent": "services"
  },
  {
    "type": "menu",
    "key": null,
    "page_name": "Worship and Spiritual Programs",
    "page-zuid": "7-fcd2eec8b2-sbgzqt",
    "sort": 5,
    "parent": "services"
  },
  {
    "type": "menu",
    "key": "about_us",
    "page_name": "About Us",
    "page-zuid": null,
    "parent": null
  },
  {
    "type": "menu",
    "key": null,
    "page_name": "About Us",
    "page-zuid": "7-ccb6d8dbec-g3k41v",
    "sort": 0,
    "parent": "about_us"
  },
  {
    "type": "menu",
    "key": null,
    "page_name": "Commitment to all",
    "page-zuid": "7-90eff9e999-tpj14d",
    "sort": 1,
    "parent": "about_us"
  },
  {
    "type": "menu",
    "key": null,
    "page_name": "Leadership",
    "page-zuid": "7-da9df9b3b3-w3ngns",
    "sort": 2,
    "parent": "about_us"
  },
  {
    "type": "menu",
    "key": null,
    "page_name": "History",
    "page-zuid": "7-b8c09b84c2-fp57hm",
    "sort": 3,
    "parent": "about_us"
  },
  {
    "type": "menu",
    "key": null,
    "page_name": "Employment Opportunities",
    "page-zuid": "7-909ec5bbc1-fv94h8",
    "sort": 4,
    "parent": "about_us"
  },
  {
    "type": "menu",
    "key": null,
    "page_name": "Give With Joy",
    "page-zuid": "give_with_joy",
    "sort": 5,
    "parent": "about_us"
  },
  {
    "type": "menu",
    "key": "events",
    "page_name": "Omaha, NE: Citadel Corps Community Center",
    "page-zuid": "7-ecfabafebf-vwlw7f",
    "parent": null
  },
  {
    "type": "menu",
    "key": "newsroom",
    "page_name": "Omaha, NE: Citadel Corps Community Center",
    "page-zuid": "7-9095cdc0c5-57cd32",
    "parent": null
  },
  {
    "type": "menu",
    "key": "ways_to_give",
    "page_name": "Ways to give",
    "page-zuid": null,
    "parent": null
  },
  {
    "type": "menu",
    "key": null,
    "page_name": "Donate Money",
    "page-zuid": "donate_money",
    "sort": 0,
    "parent": "ways_to_give"
  },
  {
    "type": "menu",
    "key": null,
    "page_name": "Donate Goods",
    "page-zuid": "donate_goods",
    "sort": 1,
    "parent": "ways_to_give"
  },
  {
    "type": "menu",
    "key": null,
    "page_name": "Become a Fundraiser",
    "page-zuid": "become_fundraiser",
    "sort": 2,
    "parent": "ways_to_give"
  },
  {
    "type": "menu",
    "key": null,
    "page_name": "Planned Giving",
    "page-zuid": "7-b2c8f8c3a1-p70t2s",
    "sort": 3,
    "parent": "ways_to_give"
  },
  {
    "type": "menu",
    "key": null,
    "page_name": "Gift Stocks & Bonds",
    "page-zuid": "7-c4bebbe989-d1cqdk",
    "sort": 4,
    "parent": "ways_to_give"
  },
  {
    "type": "menu",
    "key": null,
    "page_name": "Volunteer",
    "page-zuid": "7-988aee8a8c-1gjgr8",
    "sort": 5,
    "parent": "ways_to_give"
  },
  {
    "type": "menu",
    "key": null,
    "page_name": "View All Ways to Give",
    "page-zuid": "7-8cb6efc8b0-bw9xct",
    "sort": 6,
    "parent": "ways_to_give"
  },
  {
    "type": "menu",
    "key": "contact_us",
    "page_name": "Contact Us",
    "page-zuid": "7-86efa2bcc6-qs3ctc",
    "parent": null
  },
  {
    "type": "menu",
    "key": "custom_menu",
    "page_name": "More",
    "page-zuid": null,
    "parent": null
  },
  {
    "type": "menu",
    "key": null,
    "page_name": "Volunteer",
    "page-zuid": "7-9ec9add9c7-s9xrfn",
    "sort": 0,
    "parent": "custom_menu"
  },
  {
    "type": "menu",
    "key": null,
    "page_name": "Why the Uniform",
    "page-zuid": "7-908bb0dfcb-jkd4bv",
    "sort": 1,
    "parent": "custom_menu"
  },
  {
    "type": "menu",
    "key": null,
    "page_name": "Meet the Greatest Need",
    "page-zuid": "7-caf2c6e798-k1kwjb",
    "sort": 2,
    "parent": "custom_menu"
  }
]